multi_webbing/__init__.py
multi_webbing/multi_webbing.py
multi_webbing-0.3.0.dist-info/METADATA
multi_webbing-0.3.0.dist-info/WHEEL
multi_webbing-0.3.0.dist-info/top_level.txt
multi_webbing-0.3.0.dist-info/RECORD
