Metadata-Version: 2.1
Name: multi-webbing
Version: 0.3.0
Summary: A multi-threaded libary for web scraping in python, built upon the python threading. Supports selenium and requests.
Home-page: https://github.com/adhardy/Multi-Webbing
Author: Adam Hardy
Author-email: adamdhardy@icloud.com
License: MIT
Keywords: web-scraping,multithreading,requests
Platform: UNKNOWN
Requires-Dist: requests
